{
    "title": "careers",
    "pageType": "innerpage",
    "content": [
        {
            "id": "careers-listing",
            "section": "listing-section",
            "section_title": {
                "title": "Become a part of our big family to inspire and get inspired by <span>professional experts.</span>"
            },
            "items": [
                {
                    "id": 1,
                    "title": "Software Developer",
                    "type": "Full time / Prague, CZ",
                    "description": "Strong knowledge & experience with at least one of the programming languages: JS, Java, Python, C++, C# or Go. Algorithmic thinking, experience with design patterns and data structures, ability to cut bigger software apps with the use of industry standard frameworks."
                },
                {
                    "id": 2,
                    "title": "QA Automation Engineer",
                    "type": "Full time / Prague, CZ",
                    "description": "Experience with SW testing. Excellent logical thinking ability, good problem solving, collaboration, and communication skills."
                },
                {
                    "id": 3,
                    "title": "Junior Developer",
                    "type": "Part time / Remote",
                    "description": "Experience with at least one of the programming languages: JS, Java, Python, C++, C# or Go."
                }
            ]
        },
        {
            "id": "careers-gallery",
            "section": "gallery-section",
            "section_title": {
                "title": "Pay a visit & have some coffee!"
            },
            "buttons": [
                {
                    "id": 1,
                    "variant": "texted",
                    "path": "/leadership",
                    "icon": "far fa-long-arrow-right",
                    "icondistance": "4px",
                    "content": "View All Team"
                }
            ],
            "images": [
                {
                    "src": "../images/box-image/office-1.jpg"
                },
                {
                    "src": "../images/box-image/office-2.jpg"
                },
                {
                    "src": "../images/box-image/office-3.jpg"
                },
                {
                    "src": "../images/box-image/office-4.jpg"
                }
            ]
        },
        {
            "id": "aboutus-solution",
            "section": "solution-section",
            "headings": [
                {
                    "content": "Benefits"
                }
            ],
            "items": [
                {
                    "id": 1,
                    "title": "Career development",
                    "description": "Our service offerings cover all phases including planning, design, architecture, MVP development, QA, operation, support, and iterative evolution."
                },
                {
                    "id": 2,
                    "title": "Training and learning",
                    "description": "Develop and propose product improvements through periodical and accurate testing, repairing & refining every version."
                },
                {
                    "id": 3,
                    "title": "Vacation",
                    "description": "It's more than a responsibility but a guarantee from us to gain customer trust with highly reliable quality control system."
                },
                {
                    "id": 4,
                    "title": "Passion and excitement",
                    "description": "At Bonitoo, we have a long experience with maintenance and operation of existing systems deployed both on premise and cloud."
                },
                {
                    "id": 5,
                    "title": "Highly Professional Staffs",
                    "description": "Having obtained the official & formal training in IT technology and technical fields, our staffs know more than what they show."
                },
                {
                    "id": 6,
                    "title": "Product Management Services",
                    "description": "We offer product management services like market analysis, benchmarks, competitors, financial analysis, roadmap planning, trainings, workshops, etc."
                }
            ]
        },
        {
            "id": "faq-contact-content",
            "section": "contact-section",
            "headings": [
                {
                    "level": "h3",
                    "content": "Obtaining further information by <span>make a contact</span> with us."
                },
                {
                    "level": "h6",
                    "content": "REACH OUT NOW!"
                },
                {
                    "level": "h2",
                    "content": "info@bonitoo.io"
                }
            ],
            "texts": [
                {
                    "content": "Haven't found the position you're interested in? <br/> Send us your CV."
                }
            ],
            "buttons": [
                {
                    "id": 1,
                    "color": "secondary",
                    "hoverStyle": "three",
                    "path": "/contact-us",
                    "content": "Contact Us"
                }
            ]
        }
    ]
}
